cvsim/__init__.py
cvsim/fit_curve.py
cvsim/mechanisms.py
cvsim/py.typed
cvsim-1.0.0.dist-info/METADATA
cvsim-1.0.0.dist-info/WHEEL
cvsim-1.0.0.dist-info/licenses/LICENSE
cvsim-1.0.0.dist-info/RECORD
