Metadata-Version: 2.4
Name: cvsim
Version: 1.0.0
Summary: A package for cyclic voltammetry simulation via the semi-analytical method
Project-URL: Homepage, https://github.com/ericfell/CVsim
Project-URL: Documentation, https://cvsim.readthedocs.io/en/latest/index.html
Author-email: Eric Fell <efell@g.harvard.edu>, Jeremy Fell <jfell@sfu.ca>
License-Expression: MIT
License-File: LICENSE
Keywords: cyclic voltammetry,electrochemistry
Classifier: Operating System :: OS Independent
Classifier: Programming Language :: Python :: 3
Requires-Python: >=3.10
Requires-Dist: scipy
